README.md
setup.cfg
setup.py
ptt/__init__.py
ptt/__main__.py
ptt/article.py
ptt/download.py
ptt/page.py
ptt/parser.py
ptt/type.py
pttpost_parser.egg-info/PKG-INFO
pttpost_parser.egg-info/SOURCES.txt
pttpost_parser.egg-info/dependency_links.txt
pttpost_parser.egg-info/requires.txt
pttpost_parser.egg-info/top_level.txt